petrifyml/lightweightnn_to_onnx.py
petrifyml/mvautils_common_utils.py
petrifyml/mvautils_lgbm_to_onnx.py
petrifyml/mvautils_xgboost_to_onnx.py
petrifyml/onnx_common_utils.py
petrifyml/petrifyml_common.py
petrifyml/sklbdt_to_cpp.py
petrifyml/tmvabdt.py
petrifyml/tmvamlp_to_onnx.py
petrifyml-2.0.0.dist-info/licenses/LICENSE
petrifyml-2.0.0.dist-info/METADATA
petrifyml-2.0.0.dist-info/WHEEL
petrifyml-2.0.0.dist-info/entry_points.txt
petrifyml-2.0.0.dist-info/top_level.txt
petrifyml-2.0.0.dist-info/RECORD
