Metadata-Version: 2.4
Name: petrifyml
Version: 2.0.0
Summary: Convert volatile trained machine-learning algorithms to preservable formats. Concretely:
Author-email: Andy Buckley <andy.buckley@glasgow.ac.uk>, Louie Corpe <l.corpe@cern.ch>, Martin Habedank <martin.habedank@cern.ch>, Tomasz Procter <tomasz.procter@cern.ch>
Project-URL: Homepage, https://gitlab.com/hepcedar/petrifyml/
Project-URL: Bug Tracker, https://gitlab.com/hepcedar/petrifyml/-/issues
Classifier: Programming Language :: Python :: 3
Classifier: License :: OSI Approved :: GNU General Public License v3 (GPLv3)
Classifier: Operating System :: OS Independent
Classifier: Topic :: Scientific/Engineering :: Artificial Intelligence
Classifier: Topic :: Scientific/Engineering :: Information Analysis
Classifier: Topic :: Scientific/Engineering :: Physics
Classifier: Topic :: Software Development :: Code Generators
Requires-Python: >=3.11
License-File: LICENSE
Provides-Extra: sklbdt
Requires-Dist: scikit-learn; extra == "sklbdt"
Requires-Dist: joblib; extra == "sklbdt"
Requires-Dist: pandas; extra == "sklbdt"
Provides-Extra: lwtnn
Requires-Dist: numpy; extra == "lwtnn"
Requires-Dist: onnx; extra == "lwtnn"
Provides-Extra: tmvabdt
Requires-Dist: numpy; extra == "tmvabdt"
Provides-Extra: tmvamlp
Requires-Dist: numpy; extra == "tmvamlp"
Requires-Dist: pandas; extra == "tmvamlp"
Requires-Dist: tensorflow>=2.13.0; extra == "tmvamlp"
Requires-Dist: tf_keras; extra == "tmvamlp"
Requires-Dist: tf2onnx>=1.12; extra == "tmvamlp"
Provides-Extra: mvautils
Requires-Dist: numpy; extra == "mvautils"
Requires-Dist: onnx>=1.16.0; extra == "mvautils"
Requires-Dist: uproot; extra == "mvautils"
Provides-Extra: dev
Requires-Dist: joblib; extra == "dev"
Requires-Dist: pytest; extra == "dev"
Requires-Dist: pytest-cov; extra == "dev"
Requires-Dist: coverage; extra == "dev"
Requires-Dist: numpy; extra == "dev"
Requires-Dist: pandas; extra == "dev"
Requires-Dist: pyyaml; extra == "dev"
Requires-Dist: onnx>=1.16.0; extra == "dev"
Requires-Dist: onnxruntime>1.22.0; extra == "dev"
Requires-Dist: scikit-learn; extra == "dev"
Requires-Dist: tensorflow>=2.13.0; extra == "dev"
Requires-Dist: tf_keras; extra == "dev"
Requires-Dist: tf2onnx>=1.12; extra == "dev"
Requires-Dist: uproot; extra == "dev"
Dynamic: license-file
